lisa_plugins_shopping/urls.py
lisa_plugins_shopping/models.py
lisa_plugins_shopping/__init__.py
lisa_plugins_shopping/views.py
lisa_plugins_shopping/serializers.py
lisa_plugins_shopping/migrations/__init__.py
lisa_plugins_shopping/migrations/0001_initial.py
lisa_plugins_shopping/locale/en/LC_MESSAGES/django.po
lisa_plugins_shopping/locale/de/LC_MESSAGES/django.po
lisa_plugins_shopping/locale/fr/LC_MESSAGES/django.po
lisa_plugins_shopping-0.2.0.dist-info/RECORD
lisa_plugins_shopping-0.2.0.dist-info/metadata.json
lisa_plugins_shopping-0.2.0.dist-info/DESCRIPTION.rst
lisa_plugins_shopping-0.2.0.dist-info/METADATA
lisa_plugins_shopping-0.2.0.dist-info/entry_points.txt
lisa_plugins_shopping-0.2.0.dist-info/WHEEL
lisa_plugins_shopping-0.2.0.dist-info/pbr.json
lisa_plugins_shopping-0.2.0.dist-info/top_level.txt
