Metadata-Version: 2.0
Name: lisa-plugins-shopping
Version: 0.2.0
Summary: This plugin manage a shopping list. It let the user to add or delete items on multiple shopping list.
Home-page: https://github.com/project-lisa/lisa-plugins-shopping
Author: Julien Syx
Author-email: julien@lisa-project.net
License: Apache
Platform: UNKNOWN
Classifier: Development Status :: 2 - Pre-Alpha
Classifier: Environment :: Web Environment
Classifier: Framework :: Django
Classifier: Intended Audience :: Developers
Classifier: License :: OSI Approved :: BSD License
Classifier: Operating System :: OS Independent
Classifier: Natural Language :: English
Classifier: Programming Language :: Python :: 2
Classifier: Programming Language :: Python :: 2.7
Classifier: Programming Language :: Python :: 3
Classifier: Programming Language :: Python :: 3.4
Classifier: Topic :: Internet :: WWW/HTTP
Requires-Dist: djangorestframework
Requires-Dist: django
Requires-Dist: lisa-api
Requires-Dist: jsonfield
